MANIFEST.in
README.md
VERSION
requirements.txt
setup.py
parsepatch/__init__.py
parsepatch/patch.py
parsepatch.egg-info/PKG-INFO
parsepatch.egg-info/SOURCES.txt
parsepatch.egg-info/dependency_links.txt
parsepatch.egg-info/not-zip-safe
parsepatch.egg-info/requires.txt
parsepatch.egg-info/top_level.txt