Metadata-Version: 1.0
Name: parsepatch
Version: 0.1.3
Summary: Library to parse patches in an efficient manner
Home-page: https://github.com/mozilla/parsepatch
Author: Mozilla Release Management
Author-email: release-mgmt@mozilla.com
License: MPL
Platform: UNKNOWN
